equity_aggregator/README.md
equity_aggregator/__init__.py
equity_aggregator/logging_config.py
equity_aggregator/adapters/__init__.py
equity_aggregator/adapters/data_sources/__init__.py
equity_aggregator/adapters/data_sources/_utils/__init__.py
equity_aggregator/adapters/data_sources/_utils/_client.py
equity_aggregator/adapters/data_sources/_utils/_record_types.py
equity_aggregator/adapters/data_sources/discovery_feeds/__init__.py
equity_aggregator/adapters/data_sources/discovery_feeds/intrinio/__init__.py
equity_aggregator/adapters/data_sources/discovery_feeds/intrinio/intrinio.py
equity_aggregator/adapters/data_sources/discovery_feeds/intrinio/session.py
equity_aggregator/adapters/data_sources/discovery_feeds/intrinio/_utils/__init__.py
equity_aggregator/adapters/data_sources/discovery_feeds/intrinio/_utils/backoff.py
equity_aggregator/adapters/data_sources/discovery_feeds/intrinio/_utils/parser.py
equity_aggregator/adapters/data_sources/discovery_feeds/lseg/__init__.py
equity_aggregator/adapters/data_sources/discovery_feeds/lseg/lseg.py
equity_aggregator/adapters/data_sources/discovery_feeds/lseg/session.py
equity_aggregator/adapters/data_sources/discovery_feeds/lseg/_utils/__init__.py
equity_aggregator/adapters/data_sources/discovery_feeds/lseg/_utils/backoff.py
equity_aggregator/adapters/data_sources/discovery_feeds/lseg/_utils/parser.py
equity_aggregator/adapters/data_sources/discovery_feeds/sec/__init__.py
equity_aggregator/adapters/data_sources/discovery_feeds/sec/sec.py
equity_aggregator/adapters/data_sources/discovery_feeds/stock_analysis/__init__.py
equity_aggregator/adapters/data_sources/discovery_feeds/stock_analysis/stock_analysis.py
equity_aggregator/adapters/data_sources/discovery_feeds/tradingview/__init__.py
equity_aggregator/adapters/data_sources/discovery_feeds/tradingview/tradingview.py
equity_aggregator/adapters/data_sources/discovery_feeds/xetra/__init__.py
equity_aggregator/adapters/data_sources/discovery_feeds/xetra/xetra.py
equity_aggregator-1.0.0.dist-info/METADATA
equity_aggregator-1.0.0.dist-info/WHEEL
equity_aggregator-1.0.0.dist-info/entry_points.txt
equity_aggregator-1.0.0.dist-info/licenses/LICENCE.txt
equity_aggregator-1.0.0.dist-info/RECORD
