Metadata-Version: 2.4
Name: equity-aggregator
Version: 1.0.0
Summary: Financial equity data aggregation toolkit
Project-URL: Homepage, https://github.com/gregorykelleher/equity-aggregator
Project-URL: Repository, https://github.com/gregorykelleher/equity-aggregator
Author-email: Gregory Kelleher <gregory@gregorykelleher.com>
License-Expression: MIT
License-File: LICENCE.txt
Keywords: aggregation,data,equity,finance,financial-data
Classifier: Intended Audience :: Financial and Insurance Industry
Classifier: License :: OSI Approved :: MIT License
Classifier: Programming Language :: Python :: 3.12
Classifier: Topic :: Software Development :: Libraries :: Python Modules
Requires-Python: >=3.12.5
Requires-Dist: httpx[http2]>=0.28.1
Requires-Dist: openfigipy>=0.1.6
Requires-Dist: platformdirs>=4.0.0
Requires-Dist: pydantic>=2.11.3
Requires-Dist: rapidfuzz>=3.13.0
